Workbook

Sheet Supuestos
A1: MODELO: FLOTA PROPIA vs COURIER - CAV
A2: Edita las celdas amarillas; las demas hojas se recalculan solas.
A4: PARAMETROS GENERALES
A5: Envios por mes | B5: 15000
A6: Dias habiles por mes | B6: 22
A7: Capacidad entregas por movil/dia | B7: 120
A8: Costo courier por envio (CLP) | B8: 2980
A9: Valor UF (CLP) | B9: 40000
A10: N de moviles (escenario base) | B10: 7
A12: REPARTO Y KILOMETRAJE
A13: Km totales de reparto por mes | B13: 30000
A14: Km incluidos por movil (contrato) | B14: 3000
A15: Costo sobrekilometraje (CLP/km) | B15: 150
A17: VEHICULOS Y ENERGIA
A18: Leasing electrico (UF por movil/mes) | B18: 34
A19: Leasing petrolero (UF por movil/mes) | B19: 27
A20: Precio electricidad (CLP/kWh) | B20: 150
A21: Consumo electrico (kWh/km) | B21: 0.25
A22: Precio diesel (CLP/L) | B22: 1050
A23: Rendimiento diesel (km/L) | B23: 10
A24: Infra de carga electrica (CLP/movil/mes) | B24: 25000
A26: PERSONAL Y OVERHEAD
A27: Costo empresa conductor (CLP/mes) | B27: 1200000
A28: Peoneta: % bajo el conductor | B28: 0.3
A29: Provision multas/deducibles (CLP/mes) | B29: 500000
A30: Overhead fijo (CLP/mes) | B30: 2770000
A31: Telemetria (CLP/movil/mes) | B31: 13000
A33: PROYECCION 3 ANOS (reajustes anuales)
A34: Alza anual diesel | B34: 0.08
A35: Alza anual electricidad | B35: 0.03
A36: Reajuste anual courier | B36: 0.05
A37: Reajuste anual UF / leasing | B37: 0.035
A38: Reajuste anual sueldos / overhead | B38: 0.04

Sheet Escenarios
A1: ESCENARIOS POR TAMANO DE FLOTA (con sobrekilometraje)
A3: Moviles (N) | B3: Utilizacion | C3: Km/movil | D3: Sobrekm/mes | E3: Total Electrica/mes | F3: Total Petrolera/mes | G3: $/envio Elec. | H3: $/envio Pet. | I3: Ahorro/ano Elec. | J3: Ahorro/ano Pet.
A4: 10 | B4: =Supuestos!$B$5/(Supuestos!$B$7*Supuestos!$B$6*$A4) -> 0.56818182 | C4: =Supuestos!$B$13/$A4 -> 3000 | D4: =(MAX(0,Supuestos!$B$13-$A4*Supuestos!$B$14)*Supuestos!$B$15) -> 0 | E4: =($A4*Supuestos!$B$18*Supuestos!$B$9)+(Supuestos!$B$13*Supuestos!$B$21*Supuestos!$B$20)+($A4*Supuestos!$B$24)+($A4*Supuestos!$B$27*(2-Supuestos!$B$28))+(Supuestos!$B$30+$A4*Supuestos!$B$31)+(MAX(0,Supuestos!$B$13-$A4*Supuestos!$B$14)*Supuestos!$B$15)+Supuestos!$B$29 -> 38775000 | F4: =($A4*Supuestos!$B$19*Supuestos!$B$9)+(Supuestos!$B$13/Supuestos!$B$23*Supuestos!$B$22)+($A4*Supuestos!$B$27*(2-Supuestos!$B$28))+(Supuestos!$B$30+$A4*Supuestos!$B$31)+(MAX(0,Supuestos!$B$13-$A4*Supuestos!$B$14)*Supuestos!$B$15)+Supuestos!$B$29 -> 37750000 | G4: =E4/Supuestos!$B$5 -> 2585 | H4: =F4/Supuestos!$B$5 -> 2516.6667 | I4: =(Supuestos!$B$8*Supuestos!$B$5-E4)*12 -> 71100000 | J4: =(Supuestos!$B$8*Supuestos!$B$5-F4)*12 -> 83400000
A5: 9 | B5: =Supuestos!$B$5/(Supuestos!$B$7*Supuestos!$B$6*$A5) -> 0.63131313 | C5: =Supuestos!$B$13/$A5 -> 3333.3333 | D5: =(MAX(0,Supuestos!$B$13-$A5*Supuestos!$B$14)*Supuestos!$B$15) -> 450000 | E5: =($A5*Supuestos!$B$18*Supuestos!$B$9)+(Supuestos!$B$13*Supuestos!$B$21*Supuestos!$B$20)+($A5*Supuestos!$B$24)+($A5*Supuestos!$B$27*(2-Supuestos!$B$28))+(Supuestos!$B$30+$A5*Supuestos!$B$31)+(MAX(0,Supuestos!$B$13-$A5*Supuestos!$B$14)*Supuestos!$B$15)+Supuestos!$B$29 -> 35787000 | F5: =($A5*Supuestos!$B$19*Supuestos!$B$9)+(Supuestos!$B$13/Supuestos!$B$23*Supuestos!$B$22)+($A5*Supuestos!$B$27*(2-Supuestos!$B$28))+(Supuestos!$B$30+$A5*Supuestos!$B$31)+(MAX(0,Supuestos!$B$13-$A5*Supuestos!$B$14)*Supuestos!$B$15)+Supuestos!$B$29 -> 35067000 | G5: =E5/Supuestos!$B$5 -> 2385.8 | H5: =F5/Supuestos!$B$5 -> 2337.8 | I5: =(Supuestos!$B$8*Supuestos!$B$5-E5)*12 -> 106956000 | J5: =(Supuestos!$B$8*Supuestos!$B$5-F5)*12 -> 115596000
A6: 8 | B6: =Supuestos!$B$5/(Supuestos!$B$7*Supuestos!$B$6*$A6) -> 0.71022727 | C6: =Supuestos!$B$13/$A6 -> 3750 | D6: =(MAX(0,Supuestos!$B$13-$A6*Supuestos!$B$14)*Supuestos!$B$15) -> 900000 | E6: =($A6*Supuestos!$B$18*Supuestos!$B$9)+(Supuestos!$B$13*Supuestos!$B$21*Supuestos!$B$20)+($A6*Supuestos!$B$24)+($A6*Supuestos!$B$27*(2-Supuestos!$B$28))+(Supuestos!$B$30+$A6*Supuestos!$B$31)+(MAX(0,Supuestos!$B$13-$A6*Supuestos!$B$14)*Supuestos!$B$15)+Supuestos!$B$29 -> 32799000 | F6: =($A6*Supuestos!$B$19*Supuestos!$B$9)+(Supuestos!$B$13/Supuestos!$B$23*Supuestos!$B$22)+($A6*Supuestos!$B$27*(2-Supuestos!$B$28))+(Supuestos!$B$30+$A6*Supuestos!$B$31)+(MAX(0,Supuestos!$B$13-$A6*Supuestos!$B$14)*Supuestos!$B$15)+Supuestos!$B$29 -> 32384000 | G6: =E6/Supuestos!$B$5 -> 2186.6 | H6: =F6/Supuestos!$B$5 -> 2158.9333 | I6: =(Supuestos!$B$8*Supuestos!$B$5-E6)*12 -> 142812000 | J6: =(Supuestos!$B$8*Supuestos!$B$5-F6)*12 -> 147792000
A7: 7 | B7: =Supuestos!$B$5/(Supuestos!$B$7*Supuestos!$B$6*$A7) -> 0.81168831 | C7: =Supuestos!$B$13/$A7 -> 4285.7143 | D7: =(MAX(0,Supuestos!$B$13-$A7*Supuestos!$B$14)*Supuestos!$B$15) -> 1350000 | E7: =($A7*Supuestos!$B$18*Supuestos!$B$9)+(Supuestos!$B$13*Supuestos!$B$21*Supuestos!$B$20)+($A7*Supuestos!$B$24)+($A7*Supuestos!$B$27*(2-Supuestos!$B$28))+(Supuestos!$B$30+$A7*Supuestos!$B$31)+(MAX(0,Supuestos!$B$13-$A7*Supuestos!$B$14)*Supuestos!$B$15)+Supuestos!$B$29 -> 29811000 | F7: =($A7*Supuestos!$B$19*Supuestos!$B$9)+(Supuestos!$B$13/Supuestos!$B$23*Supuestos!$B$22)+($A7*Supuestos!$B$27*(2-Supuestos!$B$28))+(Supuestos!$B$30+$A7*Supuestos!$B$31)+(MAX(0,Supuestos!$B$13-$A7*Supuestos!$B$14)*Supuestos!$B$15)+Supuestos!$B$29 -> 29701000 | G7: =E7/Supuestos!$B$5 -> 1987.4 | H7: =F7/Supuestos!$B$5 -> 1980.0667 | I7: =(Supuestos!$B$8*Supuestos!$B$5-E7)*12 -> 178668000 | J7: =(Supuestos!$B$8*Supuestos!$B$5-F7)*12 -> 179988000
A8: 6 | B8: =Supuestos!$B$5/(Supuestos!$B$7*Supuestos!$B$6*$A8) -> 0.9469697 | C8: =Supuestos!$B$13/$A8 -> 5000 | D8: =(MAX(0,Supuestos!$B$13-$A8*Supuestos!$B$14)*Supuestos!$B$15) -> 1800000 | E8: =($A8*Supuestos!$B$18*Supuestos!$B$9)+(Supuestos!$B$13*Supuestos!$B$21*Supuestos!$B$20)+($A8*Supuestos!$B$24)+($A8*Supuestos!$B$27*(2-Supuestos!$B$28))+(Supuestos!$B$30+$A8*Supuestos!$B$31)+(MAX(0,Supuestos!$B$13-$A8*Supuestos!$B$14)*Supuestos!$B$15)+Supuestos!$B$29 -> 26823000 | F8: =($A8*Supuestos!$B$19*Supuestos!$B$9)+(Supuestos!$B$13/Supuestos!$B$23*Supuestos!$B$22)+($A8*Supuestos!$B$27*(2-Supuestos!$B$28))+(Supuestos!$B$30+$A8*Supuestos!$B$31)+(MAX(0,Supuestos!$B$13-$A8*Supuestos!$B$14)*Supuestos!$B$15)+Supuestos!$B$29 -> 27018000 | G8: =E8/Supuestos!$B$5 -> 1788.2 | H8: =F8/Supuestos!$B$5 -> 1801.2 | I8: =(Supuestos!$B$8*Supuestos!$B$5-E8)*12 -> 214524000 | J8: =(Supuestos!$B$8*Supuestos!$B$5-F8)*12 -> 212184000
A10: Courier actual (referencia): | E10: =Supuestos!$B$8*Supuestos!$B$5 -> 44700000 | G10: =Supuestos!$B$8 -> 2980

Sheet Electrica vs Courier
A1: EVALUACION: FLOTA ELECTRICA vs COURIER
A2: Moviles del escenario base (editar en Supuestos!B10): | B2: =Supuestos!$B$10 -> 7
A4: Concepto | B4: Courier | C4: Flota Electrica | D4: Diferencia
A5: Costo total / mes | B5: =Supuestos!$B$8*Supuestos!$B$5 -> 44700000 | C5: =(Supuestos!$B$10*Supuestos!$B$18*Supuestos!$B$9)+(Supuestos!$B$13*Supuestos!$B$21*Supuestos!$B$20)+(Supuestos!$B$10*Supuestos!$B$24)+(Supuestos!$B$10*Supuestos!$B$27*(2-Supuestos!$B$28))+(Supuestos!$B$30+Supuestos!$B$10*Supuestos!$B$31)+(MAX(0,Supuestos!$B$13-Supuestos!$B$10*Supuestos!$B$14)*Supuestos!$B$15)+Supuestos!$B$29 -> 29811000 | D5: =C5-B5 -> -14889000
A6: Costo por envio | B6: =Supuestos!$B$8 -> 2980 | C6: =C5/Supuestos!$B$5 -> 1987.4 | D6: =C6-B6 -> -992.6
A7: Costo total / ano | B7: =B5*12 -> 536400000 | C7: =C5*12 -> 357732000 | D7: =C7-B7 -> -178668000
A8: Reduccion de costo | D8: =(B5-C5)/B5 -> 0.33308725
A10: DESGLOSE FLOTA ELECTRICA (CLP/mes)
A11: Leasing electrico | B11: =(Supuestos!$B$10*Supuestos!$B$18*Supuestos!$B$9) -> 9520000
A12: Energia electrica | B12: =(Supuestos!$B$13*Supuestos!$B$21*Supuestos!$B$20) -> 1125000
A13: Infraestructura de carga | B13: =(Supuestos!$B$10*Supuestos!$B$24) -> 175000
A14: Conductores + peonetas | B14: =(Supuestos!$B$10*Supuestos!$B$27*(2-Supuestos!$B$28)) -> 14280000
A15: Sobrekilometraje | B15: =(MAX(0,Supuestos!$B$13-Supuestos!$B$10*Supuestos!$B$14)*Supuestos!$B$15) -> 1350000
A16: Multas / deducibles | B16: =Supuestos!$B$29 -> 500000
A17: Overhead de flota | B17: =(Supuestos!$B$30+Supuestos!$B$10*Supuestos!$B$31) -> 2861000
A18: TOTAL | B18: =SUM(B11:B17) -> 29811000
A20: METRICAS DE DECISION
A21: Ahorro / mes | B21: =B5-C5 -> 14889000
A22: Ahorro / ano | B22: =(B5-C5)*12 -> 178668000
A23: Ahorro 3 anos (nominal) | B23: =(B5-C5)*36 -> 536004000
A24: Punto de equilibrio (envios/mes) | B24: =C5/Supuestos!$B$8 -> 10003.691
A25: Capacidad de la flota (envios/mes) | B25: =Supuestos!$B$7*Supuestos!$B$6*Supuestos!$B$10 -> 18480
A26: Utilizacion actual | B26: =Supuestos!$B$5/(Supuestos!$B$7*Supuestos!$B$6*Supuestos!$B$10) -> 0.81168831
A27: Holgura para crecer (envios/mes) | B27: =Supuestos!$B$7*Supuestos!$B$6*Supuestos!$B$10-Supuestos!$B$5 -> 3480

Sheet Proyeccion 3 anos
A1: PROYECCION A 3 ANOS - CLP / ano
A2: Flota base (Supuestos!B10). El diesel sube mas rapido, por eso el electrico amplia su ventaja.
A4: CLP / ano | B4: Ano 1 | C4: Ano 2 | D4: Ano 3 | E4: Acumulado 3 anos
A5: Courier | B5: =Supuestos!$B$8*Supuestos!$B$5*12*(1+Supuestos!$B$36)^0 -> 536400000 | C5: =Supuestos!$B$8*Supuestos!$B$5*12*(1+Supuestos!$B$36)^1 -> 563220000 | D5: =Supuestos!$B$8*Supuestos!$B$5*12*(1+Supuestos!$B$36)^2 -> 591381000 | E5: =SUM(B5:D5) -> 1691001000
A6: Flota Electrica | B6: =12*((Supuestos!$B$10*Supuestos!$B$18*Supuestos!$B$9)*(1+Supuestos!$B$37)^0+(MAX(0,Supuestos!$B$13-Supuestos!$B$10*Supuestos!$B$14)*Supuestos!$B$15)*(1+Supuestos!$B$37)^0+(Supuestos!$B$13*Supuestos!$B$21*Supuestos!$B$20)*(1+Supuestos!$B$35)^0+((Supuestos!$B$10*Supuestos!$B$27*(2-Supuestos!$B$28))+(Supuestos!$B$30+Supuestos!$B$10*Supuestos!$B$31)+(Supuestos!$B$10*Supuestos!$B$24)+Supuestos!$B$29)*(1+Supuestos!$B$38)^0) -> 357732000 | C6: =12*((Supuestos!$B$10*Supuestos!$B$18*Supuestos!$B$9)*(1+Supuestos!$B$37)^1+(MAX(0,Supuestos!$B$13-Supuestos!$B$10*Supuestos!$B$14)*Supuestos!$B$15)*(1+Supuestos!$B$37)^1+(Supuestos!$B$13*Supuestos!$B$21*Supuestos!$B$20)*(1+Supuestos!$B$35)^1+((Supuestos!$B$10*Supuestos!$B$27*(2-Supuestos!$B$28))+(Supuestos!$B$30+Supuestos!$B$10*Supuestos!$B$31)+(Supuestos!$B$10*Supuestos!$B$24)+Supuestos!$B$29)*(1+Supuestos!$B$38)^1) -> 371254080 | D6: =12*((Supuestos!$B$10*Supuestos!$B$18*Supuestos!$B$9)*(1+Supuestos!$B$37)^2+(MAX(0,Supuestos!$B$13-Supuestos!$B$10*Supuestos!$B$14)*Supuestos!$B$15)*(1+Supuestos!$B$37)^2+(Supuestos!$B$13*Supuestos!$B$21*Supuestos!$B$20)*(1+Supuestos!$B$35)^2+((Supuestos!$B$10*Supuestos!$B$27*(2-Supuestos!$B$28))+(Supuestos!$B$30+Supuestos!$B$10*Supuestos!$B$31)+(Supuestos!$B$10*Supuestos!$B$24)+Supuestos!$B$29)*(1+Supuestos!$B$38)^2) -> 385290166 | E6: =SUM(B6:D6) -> 1114276246
A7: Flota Petrolera | B7: =12*((Supuestos!$B$10*Supuestos!$B$19*Supuestos!$B$9)*(1+Supuestos!$B$37)^0+(MAX(0,Supuestos!$B$13-Supuestos!$B$10*Supuestos!$B$14)*Supuestos!$B$15)*(1+Supuestos!$B$37)^0+(Supuestos!$B$13/Supuestos!$B$23*Supuestos!$B$22)*(1+Supuestos!$B$34)^0+((Supuestos!$B$10*Supuestos!$B$27*(2-Supuestos!$B$28))+(Supuestos!$B$30+Supuestos!$B$10*Supuestos!$B$31)+Supuestos!$B$29)*(1+Supuestos!$B$38)^0) -> 356412000 | C7: =12*((Supuestos!$B$10*Supuestos!$B$19*Supuestos!$B$9)*(1+Supuestos!$B$37)^1+(MAX(0,Supuestos!$B$13-Supuestos!$B$10*Supuestos!$B$14)*Supuestos!$B$15)*(1+Supuestos!$B$37)^1+(Supuestos!$B$13/Supuestos!$B$23*Supuestos!$B$22)*(1+Supuestos!$B$34)^1+((Supuestos!$B$10*Supuestos!$B$27*(2-Supuestos!$B$28))+(Supuestos!$B$30+Supuestos!$B$10*Supuestos!$B$31)+Supuestos!$B$29)*(1+Supuestos!$B$38)^1) -> 371645880 | D7: =12*((Supuestos!$B$10*Supuestos!$B$19*Supuestos!$B$9)*(1+Supuestos!$B$37)^2+(MAX(0,Supuestos!$B$13-Supuestos!$B$10*Supuestos!$B$14)*Supuestos!$B$15)*(1+Supuestos!$B$37)^2+(Supuestos!$B$13/Supuestos!$B$23*Supuestos!$B$22)*(1+Supuestos!$B$34)^2+((Supuestos!$B$10*Supuestos!$B$27*(2-Supuestos!$B$28))+(Supuestos!$B$30+Supuestos!$B$10*Supuestos!$B$31)+Supuestos!$B$29)*(1+Supuestos!$B$38)^2) -> 387591364 | E7: =SUM(B7:D7) -> 1115649244
A8: Ahorro Electrica vs Courier | B8: =B5-B6 -> 0 | C8: =C5-C6 -> 0 | D8: =D5-D6 -> 0 | E8: =E5-E6 -> 0
A9: Ahorro Petrolera vs Courier | B9: =B5-B7 -> 0 | C9: =C5-C7 -> 0 | D9: =D5-D7 -> 0 | E9: =E5-E7 -> 0
A10: Ventaja Electrica vs Petrolera | B10: =B7-B6 -> 0 | C10: =C7-C6 -> 0 | D10: =D7-D6 -> 0 | E10: =E7-E6 -> 0
A12: Nota: valor positivo = el electrico es mas barato que el petrolero ese ano.
